hdl_block_design/__init__.py
hdl_block_design/_block.py
hdl_block_design/_cli.py
hdl_block_design/_yamllable.py
hdl_block_design/py.typed
hdl_block_design/vhdl.py
hdl_block_design-0.2.0.dist-info/METADATA
hdl_block_design-0.2.0.dist-info/WHEEL
hdl_block_design-0.2.0.dist-info/entry_points.txt
hdl_block_design-0.2.0.dist-info/licenses/LICENSE
hdl_block_design-0.2.0.dist-info/RECORD
